benchmarking.py
query_sentinel2.py
geofabrics/__init__.py
geofabrics/__main__.py
geofabrics/bathymetry_estimation.py
geofabrics/dem.py
geofabrics/geometry.py
geofabrics/processor.py
geofabrics/runner.py
geofabrics/version.py
geofabrics-1.1.28.dist-info/licenses/LICENSE
geofabrics-1.1.28.dist-info/METADATA
geofabrics-1.1.28.dist-info/WHEEL
geofabrics-1.1.28.dist-info/entry_points.txt
geofabrics-1.1.28.dist-info/top_level.txt
geofabrics-1.1.28.dist-info/RECORD
