Metadata-Version: 2.4
Name: geofabrics
Version: 1.1.28
Summary: A package for creating geofabrics for flood modelling.
Author-email: Rose pearson <rose.pearson@niwa.co.nz>
License:                     GNU GENERAL PUBLIC LICENSE
Project-URL: Homepage, https://github.com/rosepearson/GeoFabrics
Project-URL: Documentation, https://rosepearson.github.io/GeoFabrics/
Keywords: GeoFabrics,DEM,Roughness,Hydrologically conditioned,LiDAR
Classifier: Development Status :: 4 - Beta
Classifier: Intended Audience :: Science/Research
Classifier: Topic :: Scientific/Engineering :: GIS
Classifier: Programming Language :: Python :: 3 :: Only
Classifier: License :: OSI Approved :: GNU General Public License v3 (GPLv3)
Classifier: Operating System :: OS Independent
Requires-Python: >=3.10
License-File: LICENSE
Requires-Dist: dask
Requires-Dist: distributed
Requires-Dist: python-pdal
Requires-Dist: rioxarray
Requires-Dist: geoapis
Requires-Dist: netcdf4
Requires-Dist: osmpythontools>=0.3.5
Requires-Dist: tomli; python_version < "3.10"
Provides-Extra: dev
Requires-Dist: black; extra == "dev"
Requires-Dist: check-manifest; extra == "dev"
Requires-Dist: python-dotenv; extra == "dev"
Requires-Dist: pip-tools; extra == "dev"
Requires-Dist: pytest; extra == "dev"
Dynamic: license-file
